oi_cli2/__init__.py
oi_cli2/__version__.py
oi_cli2/py.typed
oi_cli2/abstract/HtmlTagAbstract.py
oi_cli2/abstract/__init__.py
oi_cli2/cli/__init__.py
oi_cli2/cli/account.py
oi_cli2/cli/analyze.py
oi_cli2/cli/completion.py
oi_cli2/cli/config.py
oi_cli2/cli/constant.py
oi_cli2/cli/contest.py
oi_cli2/cli/init.py
oi_cli2/cli/lang.py
oi_cli2/cli/main.py
oi_cli2/cli/problem.py
oi_cli2/cli/reg_list.py
oi_cli2/cli/submit.py
oi_cli2/cli/t3st.py
oi_cli2/cli/template.py
oi_cli2/cli/adaptor/AtCoderAdaptor.py
oi_cli2/cli/adaptor/AtCoder_printList.py
oi_cli2/cli/adaptor/__init__.py
oi_cli2/cli/adaptor/ojman.py
oi_cli2/cli/adaptor/Codeforces/Codeforces.py
oi_cli2/cli/adaptor/Codeforces/CodeforcesAdaptor.py
oi_cli2/cli/adaptor/Codeforces/__init__.py
oi_cli2/cli/adaptor/Codeforces/contestList.py
oi_cli2/cli/adaptor/Codeforces/standing.py
oi_cli2/core/DI.py
oi_cli2/core/__init__.py
oi_cli2/core/problem.py
oi_cli2/model/Account.py
oi_cli2/model/Analyze.py
oi_cli2/model/BaseOj.py
oi_cli2/model/Contest.py
oi_cli2/model/FolderState.py
oi_cli2/model/LangKV.py
oi_cli2/model/ParseProblemResult.py
oi_cli2/model/Problem.py
oi_cli2/model/ProblemMeta.py
oi_cli2/model/Result.py
oi_cli2/model/Template.py
oi_cli2/model/TestCase.py
oi_cli2/model/__init__.py
oi_cli2/utils/FileUtil.py
oi_cli2/utils/HtmlTag.py
oi_cli2/utils/HttpUtil.py
oi_cli2/utils/HttpUtilCookiesHelper.py
oi_cli2/utils/Logger.py
oi_cli2/utils/OJUtil.py
oi_cli2/utils/Provider2.py
oi_cli2/utils/Singleton.py
oi_cli2/utils/__init__.py
oi_cli2/utils/account.py
oi_cli2/utils/analyze.py
oi_cli2/utils/async2sync.py
oi_cli2/utils/configFolder.py
oi_cli2/utils/db.py
oi_cli2/utils/diffTool.py
oi_cli2/utils/enc.py
oi_cli2/utils/force_symlink.py
oi_cli2/utils/start_terminal.py
oi_cli2/utils/template.py
oi_cli2/utils/utc2local.py
oi_cli2/utils/wsTool.py
oi_cli2/utils/consts/__init__.py
oi_cli2/utils/consts/ids.py
oi_cli2/utils/consts/platforms.py
yxr_oi_cli-0.2.2.16.dist-info/METADATA
yxr_oi_cli-0.2.2.16.dist-info/WHEEL
yxr_oi_cli-0.2.2.16.dist-info/entry_points.txt
yxr_oi_cli-0.2.2.16.dist-info/licenses/LICENSE
yxr_oi_cli-0.2.2.16.dist-info/RECORD
