Metadata-Version: 2.3
Name: yxr-oi-cli
Version: 0.2.2.16
Summary: Simple Online Judge Cli Tool
Project-URL: Homepage, https://github.com/CroMarmot/oiTerminal
Project-URL: Bug Tracker, https://github.com/CroMarmot/oiTerminal/issues
Author-email: YeXiaoRain <yexiaorain@gmail.com>
License: MIT License
License-File: LICENSE
Keywords: api,atcoder,cli,codeforces,yxr
Classifier: License :: OSI Approved :: MIT License
Classifier: Programming Language :: Python :: 3
Requires-Python: >=3.8
Requires-Dist: beautifulsoup4>=4
Requires-Dist: click>=8.1.3
Requires-Dist: lxml>=4
Requires-Dist: psutil
Requires-Dist: pycryptodome>=3.13.0
Requires-Dist: requests>=2
Requires-Dist: rich>=11.0.0
Requires-Dist: yxr-atcoder-core==0.0.3.5
Requires-Dist: yxr-codeforces-core==0.0.2.4
Provides-Extra: dev
Requires-Dist: build; extra == 'dev'
Provides-Extra: tests
Requires-Dist: build; extra == 'tests'
Requires-Dist: coverage>=6; extra == 'tests'
Requires-Dist: pytest>=7; extra == 'tests'
